{
    "OrganizationsList":[
    {
        "id": 1,
        "profile": "https://dummyimage.com/400x400/d9d9d9/fff",
        "OrganizationName":"박시현",
        "uploadedNumber": 1,
        "subscribed": "false",
        "subscriberNumber": 11
    },
    {
        "id": 2,
        "profile": "https://dummyimage.com/400x400/d9d9d9/fff",
        "OrganizationName":"김택신",
        "uploadedNumber": 2,
        "subscribed": "false",
        "subscriberNumber": 22
    },
    {
        "id": 3,
        "profile": "https://dummyimage.com/400x400/d9d9d9/fff",
        "OrganizationName":"김다희",
        "uploadedNumber": 3,
        "subscribed": "false",
        "subscriberNumber": 33
    },
    {
        "id": 4,
        "profile": "https://dummyimage.com/400x400/d9d9d9/fff",
        "OrganizationName":"배소연",
        "uploadedNumber": 4,
        "subscribed": "false",
        "subscriberNumber": 44
    },
    {
        "id": 5,
        "profile": "https://dummyimage.com/400x400/d9d9d9/fff",
        "OrganizationName":"기획자",
        "uploadedNumber": 5,
        "subscribed": "false",
        "subscriberNumber": 55
    },
    {
        "id": 6,
        "profile": "https://dummyimage.com/400x400/d9d9d9/fff",
        "OrganizationName":"디자이너",
        "uploadedNumber": 6,
        "subscribed": "false",
        "subscriberNumber": 66
    },
    {
        "id": 7,
        "profile": "https://dummyimage.com/400x400/d9d9d9/fff",
        "OrganizationName":"백엔드",
        "uploadedNumber": 7,
        "subscribed": "false",
        "subscriberNumber": 77
    }
    ]
}